django_ai_translate/__init__.py
django_ai_translate/apps.py
django_ai_translate/po_handler.py
django_ai_translate/settings.py
django_ai_translate/translator.py
django_ai_translate/management/commands/ai_translate.py
django_ai_translate/management/commands/translate_po.py
django_ai_translate-0.1.2.dist-info/licenses/LICENSE
django_ai_translate-0.1.2.dist-info/METADATA
django_ai_translate-0.1.2.dist-info/WHEEL
django_ai_translate-0.1.2.dist-info/top_level.txt
django_ai_translate-0.1.2.dist-info/RECORD
