Metadata-Version: 2.4
Name: django-ai-translate
Version: 0.1.2
Summary: Django AI Translate
Author-email: Aimé DEGBEY <aime.degbey@kodesio.com>
License: MIT License
Classifier: Environment :: Web Environment
Classifier: Framework :: Django
Classifier: Framework :: Django :: 3
Classifier: Intended Audience :: Developers
Classifier: License :: OSI Approved :: BSD License
Classifier: Operating System :: OS Independent
Classifier: Programming Language :: Python
Classifier: Programming Language :: Python :: 3
Classifier: Programming Language :: Python :: 3 :: Only
Classifier: Programming Language :: Python :: 3.10
Classifier: Programming Language :: Python :: 3.11
Classifier: Programming Language :: Python :: 3.12
Classifier: Programming Language :: Python :: 3.13
Classifier: Topic :: Internet :: WWW/HTTP
Classifier: Topic :: Internet :: WWW/HTTP :: Dynamic Content
Requires-Python: >=3.6
License-File: LICENSE
Requires-Dist: anthropic>=0.53.0
Requires-Dist: cappa>=0.27.2
Requires-Dist: django>=1.11
Requires-Dist: groq>=0.25.0
Requires-Dist: openai>=1.79.0
Requires-Dist: polib>=1.2.0
Requires-Dist: six>=1.17.0
Requires-Dist: together>=1.5.8
Requires-Dist: tqdm>=4.67.1
Requires-Dist: yaspin>=3.1.0
Dynamic: license-file
